{
  "updatedAt": "2026-05-08T11:51:53+08:00",
  "source": "IBKR Flex Activity Statement forwarded via email",
  "items": [
    {
      "ticker": "700",
      "displayTicker": "0700.HK",
      "company": "Tencent",
      "market": "HK",
      "currency": "HKD",
      "quantity": 700.0,
      "price": 463.0,
      "priceTimestamp": "2026-05-08T10:53:49+08:00",
      "marketValue": 324100.0,
      "marketValueCurrency": "HKD",
      "priceSource": "IBKR Flex",
      "portfolioSource": "IBKR Flex statement (2026-05-06)",
      "retrievedAt": "2026-05-08T10:53:49+08:00"
    },
    {
      "ticker": "9988",
      "displayTicker": "9988.HK",
      "company": "Alibaba HK",
      "market": "HK",
      "currency": "HKD",
      "quantity": 6500.0,
      "price": 134.2,
      "priceTimestamp": "2026-05-08T10:53:49+08:00",
      "marketValue": 872300.0,
      "marketValueCurrency": "HKD",
      "priceSource": "IBKR Flex",
      "portfolioSource": "IBKR Flex statement (2026-05-06)",
      "retrievedAt": "2026-05-08T10:53:49+08:00"
    },
    {
      "ticker": "AMD",
      "displayTicker": "AMD",
      "company": "Advanced Micro Devices",
      "market": "US",
      "currency": "USD",
      "quantity": 75.0,
      "price": 421.39,
      "priceTimestamp": "2026-05-08T10:53:49+08:00",
      "marketValue": 31604.25,
      "marketValueCurrency": "USD",
      "priceSource": "IBKR Flex",
      "portfolioSource": "IBKR Flex statement (2026-05-06)",
      "retrievedAt": "2026-05-08T10:53:49+08:00"
    },
    {
      "ticker": "BABA",
      "displayTicker": "BABA",
      "company": "Alibaba ADR",
      "market": "US",
      "currency": "USD",
      "quantity": 1200.0,
      "price": 141.44,
      "priceTimestamp": "2026-05-08T10:53:49+08:00",
      "marketValue": 169728.0,
      "marketValueCurrency": "USD",
      "priceSource": "IBKR Flex",
      "portfolioSource": "IBKR Flex statement (2026-05-06)",
      "retrievedAt": "2026-05-08T10:53:49+08:00"
    },
    {
      "ticker": "GOOGL",
      "displayTicker": "GOOGL",
      "company": "Alphabet",
      "market": "US",
      "currency": "USD",
      "quantity": 100.0,
      "price": 398.04,
      "priceTimestamp": "2026-05-08T10:53:49+08:00",
      "marketValue": 39804.0,
      "marketValueCurrency": "USD",
      "priceSource": "IBKR Flex",
      "portfolioSource": "IBKR Flex statement (2026-05-06)",
      "retrievedAt": "2026-05-08T10:53:49+08:00"
    },
    {
      "ticker": "H78",
      "displayTicker": "H78.SI",
      "company": "Hongkong Land",
      "market": "SG",
      "currency": "USD",
      "quantity": 1500.0,
      "price": 7.97,
      "priceTimestamp": "2026-05-08T10:53:49+08:00",
      "marketValue": 11955.0,
      "marketValueCurrency": "USD",
      "priceSource": "IBKR Flex",
      "portfolioSource": "IBKR Flex statement (2026-05-06)",
      "retrievedAt": "2026-05-08T10:53:49+08:00"
    },
    {
      "ticker": "JEPG",
      "displayTicker": "JEPG",
      "company": "JPMorgan income ETF",
      "market": "US",
      "currency": "USD",
      "quantity": 288.0,
      "price": 26.09,
      "priceTimestamp": "2026-05-08T10:53:49+08:00",
      "marketValue": 7513.92,
      "marketValueCurrency": "USD",
      "priceSource": "IBKR Flex",
      "portfolioSource": "IBKR Flex statement (2026-05-06)",
      "retrievedAt": "2026-05-08T10:53:49+08:00"
    },
    {
      "ticker": "JEPI",
      "displayTicker": "JEPI",
      "company": "JPMorgan Equity Premium Income ETF",
      "market": "US",
      "currency": "USD",
      "quantity": 400.0,
      "price": 24.65,
      "priceTimestamp": "2026-05-08T10:53:49+08:00",
      "marketValue": 9860.0,
      "marketValueCurrency": "USD",
      "priceSource": "IBKR Flex",
      "portfolioSource": "IBKR Flex statement (2026-05-06)",
      "retrievedAt": "2026-05-08T10:53:49+08:00"
    },
    {
      "ticker": "JEPQ",
      "displayTicker": "JEPQ",
      "company": "JPMorgan Nasdaq Equity Premium Income ETF",
      "market": "US",
      "currency": "USD",
      "quantity": 400.0,
      "price": 27.185,
      "priceTimestamp": "2026-05-08T10:53:49+08:00",
      "marketValue": 10874.0,
      "marketValueCurrency": "USD",
      "priceSource": "IBKR Flex",
      "portfolioSource": "IBKR Flex statement (2026-05-06)",
      "retrievedAt": "2026-05-08T10:53:49+08:00"
    },
    {
      "ticker": "SLV",
      "displayTicker": "SLV",
      "company": "iShares Silver Trust",
      "market": "US",
      "currency": "USD",
      "quantity": 500.0,
      "price": 70.13,
      "priceTimestamp": "2026-05-08T10:53:49+08:00",
      "marketValue": 35065.0,
      "marketValueCurrency": "USD",
      "priceSource": "IBKR Flex",
      "portfolioSource": "IBKR Flex statement (2026-05-06)",
      "retrievedAt": "2026-05-08T10:53:49+08:00"
    },
    {
      "ticker": "SOFI",
      "displayTicker": "SOFI",
      "company": "SoFi Technologies",
      "market": "US",
      "currency": "USD",
      "quantity": 2000.0,
      "price": 16.3,
      "priceTimestamp": "2026-05-08T10:53:49+08:00",
      "marketValue": 32600.0,
      "marketValueCurrency": "USD",
      "priceSource": "IBKR Flex",
      "portfolioSource": "IBKR Flex statement (2026-05-06)",
      "retrievedAt": "2026-05-08T10:53:49+08:00"
    }
  ]
}
